manifold_learn/__init__.py
manifold_learn-0.0.1.dist-info/LICENSE
manifold_learn-0.0.1.dist-info/METADATA
manifold_learn-0.0.1.dist-info/WHEEL
manifold_learn-0.0.1.dist-info/top_level.txt
manifold_learn-0.0.1.dist-info/RECORD
